divyaj_psee/__init__.py
divyaj_psee/divyaj_clean.py
divyaj_psee/divyaj_python.py
divyaj_psee-1.2.3.dist-info/METADATA
divyaj_psee-1.2.3.dist-info/WHEEL
divyaj_psee-1.2.3.dist-info/top_level.txt
divyaj_psee-1.2.3.dist-info/RECORD
