Metadata-Version: 2.1
Name: divyaj-psee
Version: 1.2.3
Summary: Package for connecting HDFS and JHUB
Home-page: UNKNOWN
Author: Divyaj Balivada
Author-email: b.divyajbalivada@gmail.com
License: UNKNOWN
Platform: UNKNOWN
Classifier: Programming Language :: Python :: 3
Classifier: Operating System :: OS Independent
Requires-Python: >=3
